aircloak_tools/__init__.py
aircloak_tools/aircloak_api.py
aircloak_tools/aircloak_client.py
aircloak_tools/explorer.py
aircloak_tools/explorer_client.py
aircloak_tools-0.2.2.dist-info/LICENSE
aircloak_tools-0.2.2.dist-info/WHEEL
aircloak_tools-0.2.2.dist-info/METADATA
aircloak_tools-0.2.2.dist-info/RECORD
