Metadata-Version: 2.1
Name: aircloak-tools
Version: 0.2.2
Summary: Tools for querying an Aircloak service.
Home-page: https://github.com/diffix/aircloak-tools
License: MIT
Author: dlennon
Author-email: 3168260+dandanlen@users.noreply.github.com
Requires-Python: >=3.7,<4.0
Classifier: License :: OSI Approved :: MIT License
Classifier: Programming Language :: Python :: 3
Classifier: Programming Language :: Python :: 3.7
Classifier: Programming Language :: Python :: 3.8
Classifier: Programming Language :: Python :: 3.9
Requires-Dist: pandas (>=1.0.4,<2.0.0)
Requires-Dist: psycopg2 (>=2.8.5,<3.0.0)
Requires-Dist: requests (>=2.24.0,<3.0.0)
Project-URL: Repository, https://github.com/diffix/aircloak-tools
